runner/__init__.py
runner/proc.py
runner/runner.py
yet_another_runner-0.5.0.dist-info/LICENSE
yet_another_runner-0.5.0.dist-info/METADATA
yet_another_runner-0.5.0.dist-info/WHEEL
yet_another_runner-0.5.0.dist-info/top_level.txt
yet_another_runner-0.5.0.dist-info/RECORD
